django_apis/__init__.py
django_apis/admin.py
django_apis/apps.py
django_apis/constants.py
django_apis/exceptions.py
django_apis/models.py
django_apis/openapi3.py
django_apis/protects.py
django_apis/schemas.py
django_apis/settings.py
django_apis/swagger_ui.py
django_apis/tests.py
django_apis/urls.py
django_apis/utils.py
django_apis/views.py
django_apis/helpers/__init__.py
django_apis/helpers/auth.py
django_apis/helpers/base.py
django_apis/helpers/log_request_time.py
django_apis/migrations/__init__.py
django_apis/templates/django_apis/swagger_ui.html
django_apis/templates/django_apis/swagger_ui_init.js
django_apis-0.2.16.dist-info/licenses/LICENSE
django_apis-0.2.16.dist-info/METADATA
django_apis-0.2.16.dist-info/WHEEL
django_apis-0.2.16.dist-info/top_level.txt
django_apis-0.2.16.dist-info/RECORD
