Metadata-Version: 2.4
Name: django-apis
Version: 0.2.16
Summary: 基于Django的API接口开发框架。使用pydantic做接口参数验证，自动生成swagger接口管理界面，支持多种返回体封装。
Author: rRR0VrFP
Maintainer: rRR0VrFP
License: Apache License, Version 2.0
Keywords: django apis
Classifier: Development Status :: 5 - Production/Stable
Classifier: Intended Audience :: Developers
Classifier: Topic :: Software Development :: Libraries :: Python Modules
Classifier: License :: OSI Approved :: Apache Software License
Classifier: Programming Language :: Python :: 3
Classifier: Programming Language :: Python :: 3 :: Only
License-File: LICENSE
Requires-Dist: PyYAML
Requires-Dist: django
Requires-Dist: django-environment-settings
Requires-Dist: django-static-swagger-ui
Requires-Dist: jsonpath-ng
Requires-Dist: openapi-pydantic
Requires-Dist: pydantic
Requires-Dist: zenutils
Dynamic: author
Dynamic: classifier
Dynamic: description
Dynamic: description-content-type
Dynamic: keywords
Dynamic: license
Dynamic: license-file
Dynamic: maintainer
Dynamic: requires-dist
Dynamic: summary
